<WMS_Capabilities xmlns="http://www.opengis.net/wms" xmlns:xlink="http://www.w3.org/1999/xlink" xmlns:xsi="http://www.w3.org/2001/XMLSchema-instance" version="1.3.0" xsi:schemaLocation="http://www.opengis.net/wms http://schemas.opengis.net/wms/1.3.0/capabilities_1_3_0.xsd">
  <Service>
    <Name>WMS service</Name>
    <Title>WMS/WMTS/TMS server</Title>
    <Abstract>This server provide WMS, WMTS and TMS raster and vector data broadcast</Abstract>
    <KeywordList>
      <Keyword>WMS</Keyword>
      <Keyword>WMTS</Keyword>
      <Keyword>TMS</Keyword>
    </KeywordList>
    <OnlineResource xlink:href="https://data.geopf.fr/wms-r/wms" />
    <ContactInformation>
      <ContactPersonPrimary>
        <ContactPerson />
        <ContactOrganization>ROK4 Team</ContactOrganization>
      </ContactPersonPrimary>
      <ContactPosition />
      <ContactAddress>
        <AddressType />
        <Address />
        <City />
        <StateOrProvince />
        <PostCode />
        <Country />
      </ContactAddress>
      <ContactVoiceTelephone />
      <ContactFacsimileTelephone />
      <ContactElectronicMailAddress />
    </ContactInformation>
    <Fees>none</Fees>
    <AccessConstraints>none</AccessConstraints>
    <LayerLimit>2</LayerLimit>
    <MaxWidth>10000</MaxWidth>
    <MaxHeight>10000</MaxHeight>
  </Service>
  <Capability>
    <Request>
      <GetCapabilities>
        <Format>text/xml</Format>
        <DCPType>
          <HTTP>
            <Get>
              <OnlineResource xlink:href="https://data.geopf.fr/wms-r/wms" xlink:type="simple" />
            </Get>
          </HTTP>
        </DCPType>
      </GetCapabilities>
      <GetMap>
        <Format>image/jpeg</Format>
        <Format>image/png</Format>
        <Format>image/tiff</Format>
        <Format>image/geotiff</Format>
        <Format>image/x-bil;bits=32</Format>
        <DCPType>
          <HTTP>
            <Get>
              <OnlineResource xlink:href="https://data.geopf.fr/wms-r/wms" xlink:type="simple" />
            </Get>
          </HTTP>
        </DCPType>
      </GetMap>
      <GetFeatureInfo>
        <Format>text/plain</Format>
        <Format>text/html</Format>
        <Format>text/xml</Format>
        <Format>application/xml</Format>
        <Format>application/json</Format>
        <DCPType>
          <HTTP>
            <Get>
              <OnlineResource xlink:href="https://data.geopf.fr/wms-r/wms" xlink:type="simple" />
            </Get>
          </HTTP>
        </DCPType>
      </GetFeatureInfo>
    </Request>
    <Exception>
      <Format>XML</Format>
    </Exception>
    <Layer>
      <Title>cache IGN</Title>
      <Abstract>Cache IGN</Abstract>
      <CRS>CRS:84</CRS>
      <CRS>EPSG:2154</CRS>
      <CRS>IGNF:LAMB93</CRS>
      <CRS>EPSG:21781</CRS>
      <CRS>EPSG:23030</CRS>
      <CRS>EPSG:23031</CRS>
      <CRS>EPSG:23032</CRS>
      <CRS>EPSG:27561</CRS>
      <CRS>IGNF:LAMB1</CRS>
      <CRS>EPSG:27562</CRS>
      <CRS>IGNF:LAMB2</CRS>
      <CRS>EPSG:27563</CRS>
      <CRS>IGNF:LAMB3</CRS>
      <CRS>EPSG:27564</CRS>
      <CRS>IGNF:LAMB4</CRS>
      <CRS>EPSG:27571</CRS>
      <CRS>IGNF:LAMB1C</CRS>
      <CRS>EPSG:27572</CRS>
      <CRS>IGNF:LAMB2C</CRS>
      <CRS>IGNF:LAMBE</CRS>
      <CRS>EPSG:27573</CRS>
      <CRS>IGNF:LAMB3C</CRS>
      <CRS>EPSG:27574</CRS>
      <CRS>IGNF:LAMB4C</CRS>
      <CRS>EPSG:27581</CRS>
      <CRS>EPSG:27582</CRS>
      <CRS>EPSG:27583</CRS>
      <CRS>EPSG:27584</CRS>
      <CRS>EPSG:27591</CRS>
      <CRS>EPSG:27592</CRS>
      <CRS>EPSG:27593</CRS>
      <CRS>EPSG:27594</CRS>
      <CRS>EPSG:2969</CRS>
      <CRS>IGNF:GUADFM49U20</CRS>
      <CRS>EPSG:2970</CRS>
      <CRS>IGNF:GUAD48UTM20</CRS>
      <CRS>EPSG:2971</CRS>
      <CRS>IGNF:CSG67UTM22</CRS>
      <CRS>EPSG:2972</CRS>
      <CRS>IGNF:UTM22RGFG95</CRS>
      <CRS>EPSG:2973</CRS>
      <CRS>IGNF:MART38UTM20</CRS>
      <CRS>EPSG:2975</CRS>
      <CRS>IGNF:RGR92UTM40S</CRS>
      <CRS>EPSG:2976</CRS>
      <CRS>IGNF:TAHI51UTM06S</CRS>
      <CRS>EPSG:2977</CRS>
      <CRS>EPSG:2978</CRS>
      <CRS>EPSG:2980</CRS>
      <CRS>IGNF:MAYO50UTM38S</CRS>
      <CRS>EPSG:2981</CRS>
      <CRS>EPSG:2987</CRS>
      <CRS>IGNF:STPM50UTM21</CRS>
      <CRS>EPSG:2988</CRS>
      <CRS>IGNF:WALL78UTM1S</CRS>
      <CRS>EPSG:2989</CRS>
      <CRS>EPSG:2990</CRS>
      <CRS>EPSG:3034</CRS>
      <CRS>EPSG:3035</CRS>
      <CRS>EPSG:3042</CRS>
      <CRS>EPSG:3043</CRS>
      <CRS>EPSG:3044</CRS>
      <CRS>EPSG:3170</CRS>
      <CRS>EPSG:3171</CRS>
      <CRS>EPSG:3172</CRS>
      <CRS>EPSG:32620</CRS>
      <CRS>IGNF:UTM20W84MART</CRS>
      <CRS>EPSG:32621</CRS>
      <CRS>EPSG:32622</CRS>
      <CRS>EPSG:32630</CRS>
      <CRS>IGNF:UTM30W84</CRS>
      <CRS>EPSG:32631</CRS>
      <CRS>IGNF:UTM31W84</CRS>
      <CRS>EPSG:32632</CRS>
      <CRS>IGNF:UTM32W84</CRS>
      <CRS>EPSG:32701</CRS>
      <CRS>IGNF:UTM01SW84</CRS>
      <CRS>EPSG:32705</CRS>
      <CRS>EPSG:32706</CRS>
      <CRS>EPSG:32707</CRS>
      <CRS>EPSG:32738</CRS>
      <CRS>EPSG:32739</CRS>
      <CRS>IGNF:UTM39SW84</CRS>
      <CRS>EPSG:32740</CRS>
      <CRS>EPSG:3296</CRS>
      <CRS>IGNF:RGPFUTM5S</CRS>
      <CRS>EPSG:3297</CRS>
      <CRS>IGNF:RGPFUTM6S</CRS>
      <CRS>EPSG:3298</CRS>
      <CRS>IGNF:RGPFUTM7S</CRS>
      <CRS>EPSG:3302</CRS>
      <CRS>IGNF:IGN63UTM7S</CRS>
      <CRS>EPSG:3303</CRS>
      <CRS>EPSG:3304</CRS>
      <CRS>IGNF:TAHI79UTM6S</CRS>
      <CRS>EPSG:3305</CRS>
      <CRS>EPSG:3306</CRS>
      <CRS>EPSG:3727</CRS>
      <CRS>EPSG:3857</CRS>
      <CRS>EPSG:3942</CRS>
      <CRS>IGNF:RGF93CC42</CRS>
      <CRS>EPSG:3943</CRS>
      <CRS>IGNF:RGF93CC43</CRS>
      <CRS>EPSG:3944</CRS>
      <CRS>IGNF:RGF93CC44</CRS>
      <CRS>EPSG:3945</CRS>
      <CRS>IGNF:RGF93CC45</CRS>
      <CRS>EPSG:3946</CRS>
      <CRS>IGNF:RGF93CC46</CRS>
      <CRS>EPSG:3947</CRS>
      <CRS>IGNF:RGF93CC47</CRS>
      <CRS>EPSG:3948</CRS>
      <CRS>IGNF:RGF93CC48</CRS>
      <CRS>EPSG:3949</CRS>
      <CRS>IGNF:RGF93CC49</CRS>
      <CRS>EPSG:3950</CRS>
      <CRS>IGNF:RGF93CC50</CRS>
      <CRS>EPSG:4171</CRS>
      <CRS>IGNF:RGF93G</CRS>
      <CRS>EPSG:4258</CRS>
      <CRS>EPSG:4275</CRS>
      <CRS>EPSG:4326</CRS>
      <CRS>EPSG:4463</CRS>
      <CRS>EPSG:4467</CRS>
      <CRS>IGNF:RGSPM06U21</CRS>
      <CRS>EPSG:4470</CRS>
      <CRS>EPSG:4471</CRS>
      <CRS>IGNF:RGM04UTM38S</CRS>
      <CRS>EPSG:4558</CRS>
      <CRS>EPSG:4559</CRS>
      <CRS>EPSG:4621</CRS>
      <CRS>EPSG:4622</CRS>
      <CRS>EPSG:4623</CRS>
      <CRS>EPSG:4624</CRS>
      <CRS>EPSG:4625</CRS>
      <CRS>EPSG:4626</CRS>
      <CRS>EPSG:4627</CRS>
      <CRS>EPSG:4628</CRS>
      <CRS>EPSG:4629</CRS>
      <CRS>EPSG:4630</CRS>
      <CRS>EPSG:4632</CRS>
      <CRS>EPSG:4633</CRS>
      <CRS>EPSG:4636</CRS>
      <CRS>EPSG:4637</CRS>
      <CRS>EPSG:4638</CRS>
      <CRS>EPSG:4639</CRS>
      <CRS>EPSG:4641</CRS>
      <CRS>EPSG:4642</CRS>
      <CRS>EPSG:4643</CRS>
      <CRS>EPSG:4644</CRS>
      <CRS>EPSG:4687</CRS>
      <CRS>EPSG:4688</CRS>
      <CRS>EPSG:4689</CRS>
      <CRS>EPSG:4690</CRS>
      <CRS>EPSG:4691</CRS>
      <CRS>EPSG:4692</CRS>
      <CRS>EPSG:4749</CRS>
      <CRS>EPSG:4807</CRS>
      <CRS>IGNF:CSG67GEO</CRS>
      <CRS>IGNF:GUAD48GEO</CRS>
      <CRS>IGNF:GUADFM49GEO</CRS>
      <CRS>IGNF:MART38GEO</CRS>
      <CRS>IGNF:MAYO50GEO</CRS>
      <CRS>IGNF:REUN47GAUSSL</CRS>
      <CRS>IGNF:REUN47GEO</CRS>
      <CRS>IGNF:RGFG95GEO</CRS>
      <CRS>IGNF:STPM50GEO</CRS>
      <CRS>IGNF:WGS84G</CRS>
      <Layer>
        <Name>GEOGRAPHICALGRIDSYSTEMS.ETATMAJOR10</Name>
        <Title>Carte de l'&#233;tat-major - environs de Paris (1818 - 1824)</Title>
        <Abstract>Carte des environs de Paris au 1 : 10 000 &#233;tablie entre 1818 et 1824.</Abstract>
        <EX_GeographicBoundingBox>
          <westBoundLongitude>1.826818560</westBoundLongitude>
          <eastBoundLongitude>2.797380600</eastBoundLongitude>
          <southBoundLatitude>48.384737370</southBoundLatitude>
          <northBoundLatitude>49.514153880</northBoundLatitude>
        </EX_GeographicBoundingBox>
        <BoundingBox CRS="EPSG:3857" minx="203360.511870901" miny="6171101.773973024" maxx="311402.983946982" maxy="6362557.156151623" />
        <Attribution>
          <Title>Institut national de l'information g&#233;ographique et foresti&#232;re</Title>
          <OnlineResource xlink:type="simple" xlink:href="http://www.ign.fr" />
          <LogoURL width="50" height="50">
            <Format>image/gif</Format>
            <OnlineResource xlink:type="simple" xlink:href="https://data.geopf.fr/annexes/ressources/logos/ign.gif" />
          </LogoURL>
        </Attribution>
        <Style>
          <Name>normal</Name>
          <Title>L&#233;gende g&#233;n&#233;rique</Title>
          <Abstract>Fichier de l&#233;gende g&#233;n&#233;rique &#8211; pour la compatibilit&#233; avec certains syst&#232;mes</Abstract>
          <LegendURL width="200" height="200">
            <Format>image/jpeg</Format>
            <OnlineResource xlink:type="simple" xlink:href="https://data.geopf.fr/annexes/ressources/legendes/LEGEND.jpg" />
          </LegendURL>
        </Style>
        <MinScaleDenominator>8530.918335399</MinScaleDenominator>
        <MaxScaleDenominator>8735660.375448715</MaxScaleDenominator>
      </Layer>
      <Layer>
        <Name>GEOGRAPHICALGRIDSYSTEMS.ETATMAJOR40</Name>
        <Title>Carte de l'&#233;tat-major (1820-1866)</Title>
        <Abstract>Carte fran&#231;aise en couleurs du XIX&#232; si&#232;cle en couleurs superposable aux cartes et donn&#233;es modernes.</Abstract>
        <EX_GeographicBoundingBox>
          <westBoundLongitude>-6.088888790</westBoundLongitude>
          <eastBoundLongitude>10.961009530</eastBoundLongitude>
          <southBoundLatitude>41.184408200</southBoundLatitude>
          <northBoundLatitude>51.274533800</northBoundLatitude>
        </EX_GeographicBoundingBox>
        <BoundingBox CRS="EPSG:3857" minx="-677811.999599672" miny="5039580.000160674" maxx="1220173.999459819" maxy="6670000.000859659" />
        <Attribution>
          <Title>Institut national de l'information g&#233;ographique et foresti&#232;re</Title>
          <OnlineResource xlink:type="simple" xlink:href="http://www.ign.fr" />
          <LogoURL width="50" height="50">
            <Format>image/gif</Format>
            <OnlineResource xlink:type="simple" xlink:href="https://data.geopf.fr/annexes/ressources/logos/ign.gif" />
          </LogoURL>
        </Attribution>
        <Style>
          <Name>normal</Name>
          <Title>L&#233;gende g&#233;n&#233;rique</Title>
          <Abstract>Fichier de l&#233;gende g&#233;n&#233;rique &#8211; pour la compatibilit&#233; avec certains syst&#232;mes</Abstract>
          <LegendURL width="200" height="200">
            <Format>image/jpeg</Format>
            <OnlineResource xlink:type="simple" xlink:href="https://data.geopf.fr/annexes/ressources/legendes/LEGEND.jpg" />
          </LegendURL>
        </Style>
        <MinScaleDenominator>17061.836670798</MinScaleDenominator>
        <MaxScaleDenominator>8735660.375448715</MaxScaleDenominator>
      </Layer>
      <Layer>
        <Name>GEOGRAPHICALGRIDSYSTEMS.MAPS.SCAN50.1950</Name>
        <Title>SCAN50 Historique de 1950</Title>
        <Abstract>SCAN50 produit ppar l'IGN en 1950</Abstract>
        <EX_GeographicBoundingBox>
          <westBoundLongitude>-179.499994630</westBoundLongitude>
          <eastBoundLongitude>179.499994630</eastBoundLongitude>
          <southBoundLatitude>-74.999999740</southBoundLatitude>
          <northBoundLatitude>74.999999740</northBoundLatitude>
        </EX_GeographicBoundingBox>
        <BoundingBox CRS="EPSG:3857" minx="-19981847.999606941" miny="-12932243.000164609" maxx="19981847.999606941" maxy="12932243.000164600" />
        <Attribution>
          <Title>Institut national de l'information g&#233;ographique et foresti&#232;re</Title>
          <OnlineResource xlink:type="simple" xlink:href="http://www.ign.fr" />
          <LogoURL width="50" height="50">
            <Format>image/gif</Format>
            <OnlineResource xlink:type="simple" xlink:href="https://data.geopf.fr/annexes/ressources/logos/ign.gif" />
          </LogoURL>
        </Attribution>
        <Style>
          <Name>SCAN50_1950</Name>
          <Title>SCAN 50 historique</Title>
          <Abstract>L&#233;gende des la couche SCAN 50 historique</Abstract>
          <LegendURL width="300" height="8771">
            <Format>image/png</Format>
            <OnlineResource xlink:type="simple" xlink:href="https://data.geopf.fr/annexes/ressources/legendes/GEOGRAPHICALGRIDSYSTEMS.MAPS.SCAN50.1950-legend.png" />
          </LegendURL>
        </Style>
        <Style>
          <Name>normal</Name>
          <Title>L&#233;gende g&#233;n&#233;rique</Title>
          <Abstract>Fichier de l&#233;gende g&#233;n&#233;rique &#8211; pour la compatibilit&#233; avec certains syst&#232;mes</Abstract>
          <LegendURL width="200" height="200">
            <Format>image/jpeg</Format>
            <OnlineResource xlink:type="simple" xlink:href="https://data.geopf.fr/annexes/ressources/legendes/LEGEND.jpg" />
          </LegendURL>
        </Style>
        <MinScaleDenominator>17061.836670798</MinScaleDenominator>
        <MaxScaleDenominator>69885283.003589630</MaxScaleDenominator>
      </Layer>
      <Layer>
        <Name>GEOGRAPHICALGRIDSYSTEMS.PLANIGNV2</Name>
        <Title>Plan IGN v2</Title>
        <Abstract>Cartographie multi-&#233;chelles sur le territoire national, issue des bases de donn&#233;es vecteur de l&#8217;IGN, mis &#224; jour r&#233;guli&#232;rement et r&#233;alis&#233;e selon un processus enti&#232;rement automatis&#233;.</Abstract>
        <EX_GeographicBoundingBox>
          <westBoundLongitude>-175.000000000</westBoundLongitude>
          <eastBoundLongitude>175.000000000</eastBoundLongitude>
          <southBoundLatitude>-85.000000000</southBoundLatitude>
          <northBoundLatitude>85.000000000</northBoundLatitude>
        </EX_GeographicBoundingBox>
        <BoundingBox CRS="EPSG:3857" minx="-19480910.888822876" miny="-19971868.880408570" maxx="19480910.888822876" maxy="19971868.880408563" />
        <Attribution>
          <Title>Institut national de l'information g&#233;ographique et foresti&#232;re</Title>
          <OnlineResource xlink:type="simple" xlink:href="http://www.ign.fr" />
          <LogoURL width="50" height="50">
            <Format>image/gif</Format>
            <OnlineResource xlink:type="simple" xlink:href="https://data.geopf.fr/annexes/ressources/logos/ign.gif" />
          </LogoURL>
        </Attribution>
        <Style>
          <Name>GEOGRAPHICALGRIDSYSTEMS.PLANIGNV2</Name>
          <Title>Donn&#233;es GEOGRAPHICALGRIDSYSTEMS.PLANIGNV2</Title>
          <Abstract>Style et l&#233;gende associ&#233;s au flux GEOGRAPHICALGRIDSYSTEMS.PLANIGNV2</Abstract>
          <LegendURL width="300" height="6000">
            <Format>image/png</Format>
            <OnlineResource xlink:type="simple" xlink:href="https://data.geopf.fr/annexes/ressources/legendes/GEOGRAPHICALGRIDSYSTEMS.PLANIGNV2-legend.png" />
          </LegendURL>
        </Style>
        <MinScaleDenominator>1066.364791925</MinScaleDenominator>
        <MaxScaleDenominator>559082264.028717875</MaxScaleDenominator>
      </Layer>
      <Layer>
        <Name>GEOGRAPHICALGRIDSYSTEMS.TERRIER_V1</Name>
        <Title>Plan Terrier V1 (XVIIIe si&#232;cle)</Title>
        <Abstract>Plan Terrier, cartographie ancienne du XVIII&#232;me si&#232;cle sur la Corse</Abstract>
        <EX_GeographicBoundingBox>
          <westBoundLongitude>8.362838640</westBoundLongitude>
          <eastBoundLongitude>9.752813430</eastBoundLongitude>
          <southBoundLatitude>41.256769700</southBoundLatitude>
          <northBoundLatitude>43.117404990</northBoundLatitude>
        </EX_GeographicBoundingBox>
        <BoundingBox CRS="EPSG:3857" minx="930946.938991112" miny="5050289.227149944" maxx="1085678.224829400" maxy="5329859.191288478" />
        <Attribution>
          <Title>Institut national de l'information g&#233;ographique et foresti&#232;re</Title>
          <OnlineResource xlink:type="simple" xlink:href="http://www.ign.fr" />
          <LogoURL width="50" height="50">
            <Format>image/gif</Format>
            <OnlineResource xlink:type="simple" xlink:href="https://data.geopf.fr/annexes/ressources/logos/ign.gif" />
          </LogoURL>
        </Attribution>
        <Style>
          <Name>nolegend</Name>
          <Title>Donn&#233;es sans l&#233;gende</Title>
          <Abstract>Sans aucun fichier de l&#233;gende</Abstract>
          <LegendURL width="200" height="200">
            <Format>image/jpeg</Format>
            <OnlineResource xlink:type="simple" xlink:href="https://data.geopf.fr/annexes/ressources/legendes/LEGEND.jpg" />
          </LegendURL>
        </Style>
        <MinScaleDenominator>2132.729583850</MinScaleDenominator>
        <MaxScaleDenominator>8735660.375448715</MaxScaleDenominator>
      </Layer>
      <Layer>
        <Name>GEOGRAPHICALGRIDSYSTEMS.TERRIER_V2</Name>
        <Title>Plan Terrier V2 (XVIIIe si&#232;cle)</Title>
        <Abstract>Plan Terrier, cartographie ancienne du XVIII&#232;me si&#232;cle sur la Corse version est une version num&#233;ris&#233;e par les archives militaires du Minist&#232;re de la D&#233;fense</Abstract>
        <EX_GeographicBoundingBox>
          <westBoundLongitude>8.362838480</westBoundLongitude>
          <eastBoundLongitude>9.752815870</eastBoundLongitude>
          <southBoundLatitude>41.256767760</southBoundLatitude>
          <northBoundLatitude>43.117404990</northBoundLatitude>
        </EX_GeographicBoundingBox>
        <BoundingBox CRS="EPSG:3857" minx="930946.921179994" miny="5050288.939878392" maxx="1085678.496448957" maxy="5329859.191288478" />
        <Attribution>
          <Title>Institut national de l'information g&#233;ographique et foresti&#232;re</Title>
          <OnlineResource xlink:type="simple" xlink:href="http://www.ign.fr" />
          <LogoURL width="50" height="50">
            <Format>image/gif</Format>
            <OnlineResource xlink:type="simple" xlink:href="https://data.geopf.fr/annexes/ressources/logos/ign.gif" />
          </LogoURL>
        </Attribution>
        <Style>
          <Name>nolegend</Name>
          <Title>Donn&#233;es sans l&#233;gende</Title>
          <Abstract>Sans aucun fichier de l&#233;gende</Abstract>
          <LegendURL width="200" height="200">
            <Format>image/jpeg</Format>
            <OnlineResource xlink:type="simple" xlink:href="https://data.geopf.fr/annexes/ressources/legendes/LEGEND.jpg" />
          </LegendURL>
        </Style>
        <MinScaleDenominator>8530.918335399</MinScaleDenominator>
        <MaxScaleDenominator>8735660.375448715</MaxScaleDenominator>
      </Layer>
      <Layer>
        <Name>SCAN1000_PYR-JPEG_WLD_WM</Name>
        <Title>SCAN1000 France m&#233;tropolitaine 2021 (WM)</Title>
        <Abstract>Le produit SCAN 1000&#174; version 2 est une collection d'images num&#233;riques en couleurs, obtenues par rast&#233;risation des donn&#233;es vecteur de la carte nationale France (901) &#224; l'&#233;chelle 1 :1,000,000i&#232;me. Le produit couvre l'ensemble du territoire fran&#231;ais m&#233;tropolitain et la Corse.  </Abstract>
        <EX_GeographicBoundingBox>
          <westBoundLongitude>-6.420880970</westBoundLongitude>
          <eastBoundLongitude>13.549984260</eastBoundLongitude>
          <southBoundLatitude>40.289066630</southBoundLatitude>
          <northBoundLatitude>51.444014220</northBoundLatitude>
        </EX_GeographicBoundingBox>
        <BoundingBox CRS="EPSG:3857" minx="-714769.200024620" miny="4908038.000082985" maxx="1508377.348080072" maxy="6700213.720609010" />
        <Attribution>
          <Title>Institut national de l'information g&#233;ographique et foresti&#232;re</Title>
          <OnlineResource xlink:type="simple" xlink:href="http://www.ign.fr" />
          <LogoURL width="50" height="50">
            <Format>image/gif</Format>
            <OnlineResource xlink:type="simple" xlink:href="https://data.geopf.fr/annexes/ressources/logos/ign.gif" />
          </LogoURL>
        </Attribution>
        <Style>
          <Name>SCAN1000</Name>
          <Title>L&#233;gende du 1/1000000</Title>
          <Abstract>L&#233;gende associ&#233;e au Scan1000</Abstract>
          <LegendURL width="300" height="2200">
            <Format>image/png</Format>
            <OnlineResource xlink:type="simple" xlink:href="https://data.geopf.fr/annexes/ressources/legendes/SCAN1000_PYR-JPEG_WLD_WM-legend.png" />
          </LegendURL>
        </Style>
        <MinScaleDenominator>545978.773465546</MinScaleDenominator>
        <MaxScaleDenominator>559082264.028717875</MaxScaleDenominator>
      </Layer>
      <Layer>
        <Name>SCANDEP_PYR-JPEG_FXX_WM</Name>
        <Title>SCANDEP WM FXX 2011</Title>
        <Abstract>Le produit SCAN D&#233;partemental&#174; version 3 est une collection d'images cartographiques num&#233;riques en couleur, obtenues par rast&#233;risation des donn&#233;es vecteur de la s&#233;rie &#171; Cartes d&#233;partementales &#187; &#233;dit&#233;es par l'IGN. Ces images couvrent l'ensemble du territoire fran&#231;ais m&#233;tropolitain.  </Abstract>
        <EX_GeographicBoundingBox>
          <westBoundLongitude>-6.420880970</westBoundLongitude>
          <eastBoundLongitude>11.429714270</eastBoundLongitude>
          <southBoundLatitude>40.809712670</southBoundLatitude>
          <northBoundLatitude>51.161536610</northBoundLatitude>
        </EX_GeographicBoundingBox>
        <BoundingBox CRS="EPSG:3857" minx="-714769.200024620" miny="4984314.712419308" maxx="1272349.972449013" maxy="6649917.574096406" />
        <Attribution>
          <Title>Institut national de l'information g&#233;ographique et foresti&#232;re</Title>
          <OnlineResource xlink:type="simple" xlink:href="http://www.ign.fr" />
          <LogoURL width="50" height="50">
            <Format>image/gif</Format>
            <OnlineResource xlink:type="simple" xlink:href="https://data.geopf.fr/annexes/ressources/logos/ign.gif" />
          </LogoURL>
        </Attribution>
        <Style>
          <Name>normal</Name>
          <Title>L&#233;gende g&#233;n&#233;rique</Title>
          <Abstract>Fichier de l&#233;gende g&#233;n&#233;rique &#8211; pour la compatibilit&#233; avec certains syst&#232;mes</Abstract>
          <LegendURL width="200" height="200">
            <Format>image/jpeg</Format>
            <OnlineResource xlink:type="simple" xlink:href="https://data.geopf.fr/annexes/ressources/legendes/LEGEND.jpg" />
          </LegendURL>
        </Style>
        <MinScaleDenominator>68247.346683193</MinScaleDenominator>
        <MaxScaleDenominator>559082264.028717875</MaxScaleDenominator>
      </Layer>
      <Layer>
        <Name>SCANREG_PYR-JPEG_WLD_WM</Name>
        <Title>Scan R&#233;gional FXX WM 08-2021</Title>
        <Abstract>Le produit SCAN R&#233;gional&#174; version 2 est une collection d'images cartographiques num&#233;riques en couleur, obtenues par rast&#233;risation des donn&#233;es vecteur de la s&#233;rie &#171; Cartes r&#233;gionales &#187; &#233;dit&#233;es par l'IGN. Ces images couvrent l'ensemble du territoire fran&#231;ais m&#233;tropolitain.</Abstract>
        <EX_GeographicBoundingBox>
          <westBoundLongitude>-6.420880970</westBoundLongitude>
          <eastBoundLongitude>12.137980910</eastBoundLongitude>
          <southBoundLatitude>40.809712670</southBoundLatitude>
          <northBoundLatitude>51.444124100</northBoundLatitude>
        </EX_GeographicBoundingBox>
        <BoundingBox CRS="EPSG:3857" minx="-714769.200024620" miny="4984314.712419308" maxx="1351193.854159675" maxy="6700233.345527072" />
        <Attribution>
          <Title>Institut national de l'information g&#233;ographique et foresti&#232;re</Title>
          <OnlineResource xlink:type="simple" xlink:href="http://www.ign.fr" />
          <LogoURL width="50" height="50">
            <Format>image/gif</Format>
            <OnlineResource xlink:type="simple" xlink:href="https://data.geopf.fr/annexes/ressources/logos/ign.gif" />
          </LogoURL>
        </Attribution>
        <Style>
          <Name>SCANREG</Name>
          <Title>L&#233;gende du 1/1000000</Title>
          <Abstract>L&#233;gende associ&#233;e au SCANREGIONAL</Abstract>
          <LegendURL width="300" height="2200">
            <Format>image/png</Format>
            <OnlineResource xlink:type="simple" xlink:href="https://data.geopf.fr/annexes/ressources/legendes/SCANREG_PYR-JPEG_WLD_WM-legend.png" />
          </LegendURL>
        </Style>
        <MinScaleDenominator>136494.693366386</MinScaleDenominator>
        <MaxScaleDenominator>559082264.028717875</MaxScaleDenominator>
      </Layer>
    </Layer>
  </Capability>
</WMS_Capabilities>